async_essentials/__init__.py
async_essentials/_auth.py
async_essentials/_client.py
async_essentials/_config.py
async_essentials/_const.py
async_essentials/_enforcer.py
async_essentials/_exceptions.py
async_essentials/_meta.py
async_essentials/_mixins.py
async_essentials/_protocols.py
async_essentials/_request.py
async_essentials/_response.py
async_essentials/_strategies.py
async_essentials/_types.py
async_essentials/_utils.py
async_essentials/endpoints/__init__.py
async_essentials/endpoints/_authentication_endpoint.py
async_essentials/endpoints/_billing_endpoint.py
async_essentials/endpoints/_dkim_endpoint.py
async_essentials/endpoints/_domain_verification_endpoint.py
async_essentials/endpoints/_domains_endpoint.py
async_essentials/endpoints/_email_tagging_endpoint.py
async_essentials/endpoints/_endpoints_endpoint.py
async_essentials/endpoints/_features_endpoint.py
async_essentials/endpoints/_licensing_endpoint.py
async_essentials/endpoints/_me_endpoint.py
async_essentials/endpoints/_orgs_endpoint.py
async_essentials/endpoints/_package_endpoint.py
async_essentials/endpoints/_products_endpoint.py
async_essentials/endpoints/_reporting_endpoint.py
async_essentials/endpoints/_route.py
async_essentials/endpoints/_sender_lists_endpoint.py
async_essentials/endpoints/_settings_endpoint.py
async_essentials/endpoints/_stats_endpoint.py
async_essentials/endpoints/_token_endpoint.py
async_essentials/endpoints/_users_endpoint.py
async_essentials/models/__init__.py
async_essentials/models/_choice_types.py
async_essentials/models/_features.py
async_essentials/models/_me.py
async_essentials/models/_products.py
async_essentials/models/_resource.py
async_essentials-0.1.0.dist-info/LICENSE
async_essentials-0.1.0.dist-info/WHEEL
async_essentials-0.1.0.dist-info/METADATA
async_essentials-0.1.0.dist-info/RECORD
