Metadata-Version: 2.1
Name: async-essentials
Version: 0.1.0
Summary: An asynchronous python client for the proof point essentials API
Author: symonk
Requires-Python: >=3.8,<4.0
Classifier: Programming Language :: Python :: 3
Classifier: Programming Language :: Python :: 3.8
Classifier: Programming Language :: Python :: 3.9
Classifier: Programming Language :: Python :: 3.10
Classifier: Programming Language :: Python :: 3.11
Requires-Dist: httpx (>=0.23.1,<0.24.0)
